chowclassifier/__init__.py
chowclassifier/__main__.py
chowclassifier/chewdata.py
chowclassifier/chow.py
chowclassifier/utilities.py
chowclassifier-1.1.0.dist-info/licenses/LICENSE
chowclassifier-1.1.0.dist-info/METADATA
chowclassifier-1.1.0.dist-info/WHEEL
chowclassifier-1.1.0.dist-info/entry_points.txt
chowclassifier-1.1.0.dist-info/top_level.txt
chowclassifier-1.1.0.dist-info/RECORD
