Metadata-Version: 2.4
Name: chowclassifier
Version: 1.1.0
Summary: Classification of time trends using Chow test
Author-email: Luc Miaz <luc@miaz.ch>
License-Expression: CC-BY-NC-4.0
Project-URL: Homepage, https://chowclassifier.readthedocs.io/en/latest/
Project-URL: GitLab, https://gitlab.com/lucmiaz/chowclassifier
Keywords: chow,time-trends
Classifier: Programming Language :: Python
Classifier: Natural Language :: English
Classifier: Development Status :: 4 - Beta
Classifier: Programming Language :: Python :: 3
Requires-Python: >=3.6
License-File: LICENSE
Requires-Dist: matplotlib>=3.5.0
Requires-Dist: numpy>=1.19.4
Requires-Dist: pandas>=1.1.5
Requires-Dist: openpyxl
Requires-Dist: scipy>=1.1.5
Requires-Dist: seaborn>=0.11.2
Requires-Dist: statsmodels>=0.13.1
Requires-Dist: tqdm>=4.65.0
Provides-Extra: dev
Requires-Dist: pytest; extra == "dev"
Dynamic: license-file
